{"nodes": [{"id": "d_new_lib_core_utils_app_strings_dart", "label": "app_strings.dart", "file_type": "code", "source_file": "lib/core/utils/app_strings.dart", "source_location": null}, {"id": "utils_app_strings_appstrings", "label": "AppStrings", "file_type": "code", "source_file": "lib/core/utils/app_strings.dart", "source_location": null}, {"id": "utils_app_strings_lang", "label": "_lang", "file_type": "code", "source_file": "lib/core/utils/app_strings.dart", "source_location": null}, {"id": "static_string", "label": "static String", "file_type": "code", "source_file": null, "source_location": null}, {"id": "utils_app_strings_currentlanguage", "label": "currentLanguage", "file_type": "code", "source_file": "lib/core/utils/app_strings.dart", "source_location": null}, {"id": "static_string_get", "label": "static String get", "file_type": "code", "source_file": null, "source_location": null}, {"id": "utils_app_strings_strings", "label": "_strings", "file_type": "code", "source_file": "lib/core/utils/app_strings.dart", "source_location": null}, {"id": "static_final", "label": "static final", "file_type": "code", "source_file": null, "source_location": null}, {"id": "utils_app_strings_setlanguage", "label": "setLanguage", "file_type": "code", "source_file": "lib/core/utils/app_strings.dart", "source_location": null}], "edges": [{"source": "d_new_lib_core_utils_app_strings_dart", "target": "utils_app_strings_appstrings", "relation": "defines", "confidence": "EXTRACTED", "confidence_score": 1.0, "source_file": "lib/core/utils/app_strings.dart", "source_location": null, "weight": 1.0}, {"source": "d_new_lib_core_utils_app_strings_dart", "target": "utils_app_strings_lang", "relation": "defines", "confidence": "EXTRACTED", "confidence_score": 1.0, "source_file": "lib/core/utils/app_strings.dart", "source_location": null, "weight": 1.0}, {"source": "d_new_lib_core_utils_app_strings_dart", "target": "static_string", "relation": "references", "confidence": "EXTRACTED", "confidence_score": 1.0, "source_file": "lib/core/utils/app_strings.dart", "source_location": null, "weight": 1.0, "context": "variable_type"}, {"source": "d_new_lib_core_utils_app_strings_dart", "target": "utils_app_strings_currentlanguage", "relation": "defines", "confidence": "EXTRACTED", "confidence_score": 1.0, "source_file": "lib/core/utils/app_strings.dart", "source_location": null, "weight": 1.0}, {"source": "d_new_lib_core_utils_app_strings_dart", "target": "static_string_get", "relation": "references", "confidence": "EXTRACTED", "confidence_score": 1.0, "source_file": "lib/core/utils/app_strings.dart", "source_location": null, "weight": 1.0, "context": "variable_type"}, {"source": "d_new_lib_core_utils_app_strings_dart", "target": "utils_app_strings_strings", "relation": "defines", "confidence": "EXTRACTED", "confidence_score": 1.0, "source_file": "lib/core/utils/app_strings.dart", "source_location": null, "weight": 1.0}, {"source": "d_new_lib_core_utils_app_strings_dart", "target": "static_final", "relation": "references", "confidence": "EXTRACTED", "confidence_score": 1.0, "source_file": "lib/core/utils/app_strings.dart", "source_location": null, "weight": 1.0, "context": "variable_type"}, {"source": "d_new_lib_core_utils_app_strings_dart", "target": "utils_app_strings_setlanguage", "relation": "defines", "confidence": "EXTRACTED", "confidence_score": 1.0, "source_file": "lib/core/utils/app_strings.dart", "source_location": null, "weight": 1.0}]}